report.py
race_rep-0.0.1.dist-info/LICENSE
race_rep-0.0.1.dist-info/METADATA
race_rep-0.0.1.dist-info/WHEEL
race_rep-0.0.1.dist-info/top_level.txt
race_rep-0.0.1.dist-info/RECORD
