Metadata-Version: 2.1
Name: race-rep
Version: 0.0.1
Summary: F1 race report training package
Home-page: https://git.foxminded.com.ua/Asomchik/task-06.git
Author: Asomchik
Author-email: asomchik@gmail.com
License: UNKNOWN
Platform: UNKNOWN
Classifier: Programming Language :: Python :: 3
Classifier: License :: OSI Approved :: MIT License
Classifier: Operating System :: OS Independent
License-File: LICENSE
